{
  "i": {
    "py/object": "feature.Feature",
    "value": "i",
    "ftype": "grapheme",
    "start_weight": 10,
    "change_rate": 1,
    "current_weight": 10
  },
  "u": {
    "py/object": "feature.Feature",
    "value": "u",
    "ftype": "grapheme",
    "start_weight": 10,
    "change_rate": 1,
    "current_weight": 10
  },
  "\u016b": {
    "py/object": "feature.Feature",
    "value": "\u016b",
    "ftype": "grapheme",
    "start_weight": 10,
    "change_rate": 1,
    "current_weight": 10
  },
  "e": {
    "py/object": "feature.Feature",
    "value": "e",
    "ftype": "grapheme",
    "start_weight": 10,
    "change_rate": 1,
    "current_weight": 10
  },
  "\u0113": {
    "py/object": "feature.Feature",
    "value": "\u0113",
    "ftype": "grapheme",
    "start_weight": 10,
    "change_rate": 1,
    "current_weight": 10
  },
  "\u00e2": {
    "py/object": "feature.Feature",
    "value": "\u00e2",
    "ftype": "grapheme",
    "start_weight": 10,
    "change_rate": 1,
    "current_weight": 10
  },
  "\u014d": {
    "py/object": "feature.Feature",
    "value": "\u014d",
    "ftype": "grapheme",
    "start_weight": 10,
    "change_rate": 1,
    "current_weight": 10
  },
  "a": {
    "py/object": "feature.Feature",
    "value": "a",
    "ftype": "grapheme",
    "start_weight": 10,
    "change_rate": 1,
    "current_weight": 10
  },
  "\u0101": {
    "py/object": "feature.Feature",
    "value": "\u0101",
    "ftype": "grapheme",
    "start_weight": 10,
    "change_rate": 1,
    "current_weight": 10
  },
  "p": {
    "py/object": "feature.Feature",
    "value": "p",
    "ftype": "grapheme",
    "start_weight": 10,
    "change_rate": 1,
    "current_weight": 10
  },
  "t": {
    "py/object": "feature.Feature",
    "value": "t",
    "ftype": "grapheme",
    "start_weight": 10,
    "change_rate": 1,
    "current_weight": 10
  },
  "k": {
    "py/object": "feature.Feature",
    "value": "k",
    "ftype": "grapheme",
    "start_weight": 10,
    "change_rate": 1,
    "current_weight": 10
  },
  "m": {
    "py/object": "feature.Feature",
    "value": "m",
    "ftype": "grapheme",
    "start_weight": 10,
    "change_rate": 1,
    "current_weight": 10
  },
  "n": {
    "py/object": "feature.Feature",
    "value": "n",
    "ftype": "grapheme",
    "start_weight": 10,
    "change_rate": 1,
    "current_weight": 10
  },
  "s": {
    "py/object": "feature.Feature",
    "value": "s",
    "ftype": "grapheme",
    "start_weight": 10,
    "change_rate": 1,
    "current_weight": 10
  },
  "w": {
    "py/object": "feature.Feature",
    "value": "w",
    "ftype": "grapheme",
    "start_weight": 10,
    "change_rate": 1,
    "current_weight": 10
  },
  "r": {
    "py/object": "feature.Feature",
    "value": "r",
    "ftype": "grapheme",
    "start_weight": 10,
    "change_rate": 1,
    "current_weight": 10
  },
  "l": {
    "py/object": "feature.Feature",
    "value": "l",
    "ftype": "grapheme",
    "start_weight": 10,
    "change_rate": 1,
    "current_weight": 10
  },
  "sh": {
    "py/object": "feature.Feature",
    "value": "sh",
    "ftype": "grapheme",
    "start_weight": 10,
    "change_rate": 1,
    "current_weight": 10
  },
  "ps": {
    "py/object": "feature.Feature",
    "value": "ps",
    "ftype": "grapheme",
    "start_weight": 10,
    "change_rate": 1,
    "current_weight": 10
  },
  "pr": {
    "py/object": "feature.Feature",
    "value": "pr",
    "ftype": "grapheme",
    "start_weight": 10,
    "change_rate": 1,
    "current_weight": 10
  },
  "pl": {
    "py/object": "feature.Feature",
    "value": "pl",
    "ftype": "grapheme",
    "start_weight": 10,
    "change_rate": 1,
    "current_weight": 10
  },
  "ts": {
    "py/object": "feature.Feature",
    "value": "ts",
    "ftype": "grapheme",
    "start_weight": 10,
    "change_rate": 1,
    "current_weight": 10
  },
  "tsh": {
    "py/object": "feature.Feature",
    "value": "tsh",
    "ftype": "grapheme",
    "start_weight": 10,
    "change_rate": 1,
    "current_weight": 10
  },
  "tl": {
    "py/object": "feature.Feature",
    "value": "tl",
    "ftype": "grapheme",
    "start_weight": 10,
    "change_rate": 1,
    "current_weight": 10
  },
  "ks": {
    "py/object": "feature.Feature",
    "value": "ks",
    "ftype": "grapheme",
    "start_weight": 10,
    "change_rate": 1,
    "current_weight": 10
  },
  "ksh": {
    "py/object": "feature.Feature",
    "value": "ksh",
    "ftype": "grapheme",
    "start_weight": 10,
    "change_rate": 1,
    "current_weight": 10
  },
  "CV": {
    "py/object": "feature.Feature",
    "value": "CV",
    "ftype": "syllable_structure",
    "start_weight": 10,
    "change_rate": 1,
    "current_weight": 10
  },
  "V": {
    "py/object": "feature.Feature",
    "value": "V",
    "ftype": "syllable_structure",
    "start_weight": 10,
    "change_rate": 1,
    "current_weight": 10
  }
}